netbox_cisco_support/__init__.py
netbox_cisco_support/admin.py
netbox_cisco_support/models.py
netbox_cisco_support/template_content.py
netbox_cisco_support/version.py
netbox_cisco_support/management/__init__.py
netbox_cisco_support/management/commands/__init__.py
netbox_cisco_support/management/commands/sync_eox_data.py
netbox_cisco_support/migrations/0001_initial.py
netbox_cisco_support/migrations/0002_ciscodevicetypesupport.py
netbox_cisco_support/migrations/0003_auto_20210722_1917.py
netbox_cisco_support/migrations/0004_ciscosupport_is_covered.py
netbox_cisco_support/migrations/0005_auto_20210914_1344.py
netbox_cisco_support/migrations/0006_auto_20210921_0941.py
netbox_cisco_support/migrations/__init__.py
netbox_cisco_support/templates/netbox_cisco_support/cisco_support_device.html
netbox_cisco_support/templates/netbox_cisco_support/cisco_support_device_type.html
netbox_cisco_support/templatetags/__init__.py
netbox_cisco_support/templatetags/filters.py
netbox_cisco_support-0.6.dist-info/LICENSE
netbox_cisco_support-0.6.dist-info/METADATA
netbox_cisco_support-0.6.dist-info/WHEEL
netbox_cisco_support-0.6.dist-info/top_level.txt
netbox_cisco_support-0.6.dist-info/RECORD
