Metadata-Version: 2.1
Name: netbox-cisco-support
Version: 0.6
Summary: Implementing Cisco Support APIs into NetBox
Home-page: https://github.com/goebelmeier/netbox-cisco-support
Author: Timo Reimann
Author-email: timo@goebelmeier.de
License: Apache 2.0
Project-URL: Bug Tracker, https://github.com/goebelmeier/netbox-cisco-support/issues
Platform: UNKNOWN
Classifier: Development Status :: 4 - Beta
Classifier: Framework :: Django
Classifier: Intended Audience :: Information Technology
Classifier: License :: OSI Approved :: Apache Software License
Classifier: Programming Language :: Python :: 3
Classifier: Operating System :: OS Independent
Classifier: Topic :: System :: Networking
Classifier: Topic :: System :: Systems Administration
License-File: LICENSE
